{
  "bg": 134, 
  "temp": "absolute", 
  "snoozeBG": 225, 
  "recieved": true, 
  "predBGs": {
    "COB": [
      134, 
      134, 
      136, 
      140, 
      148, 
      158, 
      171, 
      186, 
      205, 
      225, 
      249, 
      252, 
      256, 
      259, 
      262, 
      265, 
      267, 
      270, 
      273, 
      275, 
      278, 
      280, 
      283, 
      285, 
      288, 
      290, 
      293, 
      295, 
      297, 
      300, 
      302
    ], 
    "aCOB": [
      134, 
      140, 
      149, 
      160, 
      174, 
      190, 
      208, 
      229, 
      253, 
      278, 
      307, 
      315, 
      322, 
      330, 
      337, 
      343, 
      349, 
      355, 
      361, 
      366, 
      371, 
      376, 
      381, 
      385, 
      390, 
      394, 
      397, 
      401
    ], 
    "IOB": [
      134, 
      133, 
      135, 
      139, 
      146, 
      155, 
      166, 
      180, 
      196, 
      215, 
      236, 
      237, 
      238, 
      238, 
      239
    ]
  }, 
  "rate": 1.85, 
  "reason": "COB: 19, Dev: 7, BGI: -3.46, ISF: 44, Target: 103; Eventual BG 302 > 103 but Min. Delta -4.00 < Exp. Delta -2.7; setting current basal of 1.85 as temp", 
  "COB": 19, 
  "eventualBG": 302, 
  "timestamp": "2016-10-14T23:04:54.170518", 
  "duration": 30, 
  "tick": -4, 
  "IOB": 1.072
}