[{"_id":"57f7ea1818a6c1577fc9e922","sgv":109,"date":1475865021000,"dateString":"2016-10-07T18:30:21.000Z","trend":4,"direction":"Flat","device":"share2","type":"sgv"},{"_id":"57f7e8ec18a6c1577fc9e921","sgv":110,"date":1475864721000,"dateString":"2016-10-07T18:25:21.000Z","trend":4,"direction":"Flat","device":"share2","type":"sgv"},{"_id":"57f7e7c018a6c1577fc9e91d","sgv":111,"date":1475864421000,"dateString":"2016-10-07T18:20:21.000Z","trend":4,"direction":"Flat","device":"share2","type":"sgv"},{"_id":"57f7e69418a6c1577fc9e919","sgv":112,"date":1475864120000,"dateString":"2016-10-07T18:15:20.000Z","trend":4,"direction":"Flat","device":"share2","type":"sgv"},{"_id":"57f7e56818a6c1577fc9e915","sgv":115,"date":1475863820000,"dateString":"2016-10-07T18:10:20.000Z","trend":4,"direction":"Flat","device":"share2","type":"sgv"},{"_id":"57f7e43c18a6c1577fc9e914","sgv":113,"date":1475863520000,"dateString":"2016-10-07T18:05:20.000Z","trend":4,"direction":"Flat","device":"share2","type":"sgv"},{"_id":"57f7e31018a6c1577fc9e910","sgv":116,"date":1475863220000,"dateString":"2016-10-07T18:00:20.000Z","trend":4,"direction":"Flat","device":"share2","type":"sgv"},{"_id":"57f7e1e418a6c1577fc9e90f","sgv":114,"date":1475862920000,"dateString":"2016-10-07T17:55:20.000Z","trend":4,"direction":"Flat","device":"share2","type":"sgv"},{"_id":"57f7e0b818a6c1577fc9e90e","sgv":114,"date":1475862621000,"dateString":"2016-10-07T17:50:21.000Z","trend":4,"direction":"Flat","device":"share2","type":"sgv"},{"_id":"57f7df8c18a6c1577fc9e90a","sgv":115,"date":1475862320000,"dateString":"2016-10-07T17:45:20.000Z","trend":4,"direction":"Flat","device":"share2","type":"sgv"},{"_id":"57f7de6018a6c1577fc9e903","sgv":113,"date":1475862022000,"dateString":"2016-10-07T17:40:22.000Z","trend":4,"direction":"Flat","device":"share2","type":"sgv"},{"_id":"57f7dd3418a6c1577fc9e8fe","sgv":113,"date":1475861721000,"dateString":"2016-10-07T17:35:21.000Z","trend":4,"direction":"Flat","device":"share2","type":"sgv"},{"_id":"57f7dc0818a6c1577fc9e8f8","sgv":115,"date":1475861420000,"dateString":"2016-10-07T17:30:20.000Z","trend":4,"direction":"Flat","device":"share2","type":"sgv"},{"_id":"57f7dadc18a6c1577fc9e8f1","sgv":114,"date":1475861120000,"dateString":"2016-10-07T17:25:20.000Z","trend":4,"direction":"Flat","device":"share2","type":"sgv"},{"_id":"57f7d9b018a6c1577fc9e8ed","sgv":113,"date":1475860821000,"dateString":"2016-10-07T17:20:21.000Z","trend":4,"direction":"Flat","device":"share2","type":"sgv"},{"_id":"57f7d88418a6c1577fc9e8e9","sgv":111,"date":1475860523000,"dateString":"2016-10-07T17:15:23.000Z","trend":4,"direction":"Flat","device":"share2","type":"sgv"},{"_id":"57f7d75818a6c1577fc9e8e5","sgv":111,"date":1475860221000,"dateString":"2016-10-07T17:10:21.000Z","trend":4,"direction":"Flat","device":"share2","type":"sgv"},{"_id":"57f7d62c18a6c1577fc9e8e1","sgv":107,"date":1475859921000,"dateString":"2016-10-07T17:05:21.000Z","trend":4,"direction":"Flat","device":"share2","type":"sgv"},{"_id":"57f7d50018a6c1577fc9e8e0","sgv":103,"date":1475859621000,"dateString":"2016-10-07T17:00:21.000Z","trend":4,"direction":"Flat","device":"share2","type":"sgv"},{"_id":"57f7d3d418a6c1577fc9e8dc","sgv":105,"date":1475859321000,"dateString":"2016-10-07T16:55:21.000Z","trend":4,"direction":"Flat","device":"share2","type":"sgv"},{"_id":"57f7d2a818a6c1577fc9e8db","sgv":109,"date":1475859021000,"dateString":"2016-10-07T16:50:21.000Z","trend":4,"direction":"Flat","device":"share2","type":"sgv"},{"_id":"57f7d17c18a6c1577fc9e8da","sgv":113,"date":1475858721000,"dateString":"2016-10-07T16:45:21.000Z","trend":4,"direction":"Flat","device":"share2","type":"sgv"},{"_id":"57f7d05018a6c1577fc9e8d9","sgv":116,"date":1475858422000,"dateString":"2016-10-07T16:40:22.000Z","trend":4,"direction":"Flat","device":"share2","type":"sgv"},{"_id":"57f7cf2418a6c1577fc9e8d5","sgv":113,"date":1475858121000,"dateString":"2016-10-07T16:35:21.000Z","trend":4,"direction":"Flat","device":"share2","type":"sgv"},{"_id":"57f7cdf818a6c1577fc9e8d3","sgv":110,"date":1475857821000,"dateString":"2016-10-07T16:30:21.000Z","trend":4,"direction":"Flat","device":"share2","type":"sgv"},{"_id":"57f7cccc18a6c1577fc9e8d0","sgv":109,"date":1475857523000,"dateString":"2016-10-07T16:25:23.000Z","trend":4,"direction":"Flat","device":"share2","type":"sgv"},{"_id":"57f7cba018a6c1577fc9e8cf","sgv":111,"date":1475857222000,"dateString":"2016-10-07T16:20:22.000Z","trend":4,"direction":"Flat","device":"share2","type":"sgv"},{"_id":"57f7ca7418a6c1577fc9e8ce","sgv":111,"date":1475856921000,"dateString":"2016-10-07T16:15:21.000Z","trend":4,"direction":"Flat","device":"share2","type":"sgv"},{"_id":"57f7c94818a6c1577fc9e8ca","sgv":113,"date":1475856620000,"dateString":"2016-10-07T16:10:20.000Z","trend":4,"direction":"Flat","device":"share2","type":"sgv"},{"_id":"57f7c81c18a6c1577fc9e8c6","sgv":111,"date":1475856322000,"dateString":"2016-10-07T16:05:22.000Z","trend":4,"direction":"Flat","device":"share2","type":"sgv"},{"_id":"57f7c6ef18a6c1577fc9e8c2","sgv":105,"date":1475856024000,"dateString":"2016-10-07T16:00:24.000Z","trend":4,"direction":"Flat","device":"share2","type":"sgv"},{"_id":"57f7c5c318a6c1577fc9e8be","sgv":108,"date":1475855723000,"dateString":"2016-10-07T15:55:23.000Z","trend":4,"direction":"Flat","device":"share2","type":"sgv"},{"_id":"57f7c49718a6c1577fc9e8ba","sgv":110,"date":1475855422000,"dateString":"2016-10-07T15:50:22.000Z","trend":4,"direction":"Flat","device":"share2","type":"sgv"},{"_id":"57f7c36b18a6c1577fc9e8b9","sgv":110,"date":1475855122000,"dateString":"2016-10-07T15:45:22.000Z","trend":4,"direction":"Flat","device":"share2","type":"sgv"},{"_id":"57f7c23f18a6c1577fc9e8b8","sgv":110,"date":1475854821000,"dateString":"2016-10-07T15:40:21.000Z","trend":4,"direction":"Flat","device":"share2","type":"sgv"},{"_id":"57f7c11318a6c1577fc9e8b7","sgv":110,"date":1475854521000,"dateString":"2016-10-07T15:35:21.000Z","trend":4,"direction":"Flat","device":"share2","type":"sgv"},{"_id":"57f7bfe718a6c1577fc9e8b3","sgv":109,"date":1475854223000,"dateString":"2016-10-07T15:30:23.000Z","trend":4,"direction":"Flat","device":"share2","type":"sgv"},{"_id":"57f7bebc18a6c1577fc9e8af","sgv":109,"date":1475853921000,"dateString":"2016-10-07T15:25:21.000Z","trend":4,"direction":"Flat","device":"share2","type":"sgv"},{"_id":"57f7bd8f18a6c1577fc9e8ab","sgv":116,"date":1475853622000,"dateString":"2016-10-07T15:20:22.000Z","trend":4,"direction":"Flat","device":"share2","type":"sgv"},{"_id":"57f7bc6318a6c1577fc9e8aa","sgv":119,"date":1475853321000,"dateString":"2016-10-07T15:15:21.000Z","trend":4,"direction":"Flat","device":"share2","type":"sgv"},{"_id":"57f7bb3718a6c1577fc9e8a9","sgv":116,"date":1475853022000,"dateString":"2016-10-07T15:10:22.000Z","trend":4,"direction":"Flat","device":"share2","type":"sgv"},{"_id":"57f7ba0b18a6c1577fc9e8a5","sgv":120,"date":1475852721000,"dateString":"2016-10-07T15:05:21.000Z","trend":4,"direction":"Flat","device":"share2","type":"sgv"},{"_id":"57f7b8df18a6c1577fc9e8a4","sgv":119,"date":1475852421000,"dateString":"2016-10-07T15:00:21.000Z","trend":4,"direction":"Flat","device":"share2","type":"sgv"},{"_id":"57f7b7b318a6c1577fc9e8a3","sgv":114,"date":1475852122000,"dateString":"2016-10-07T14:55:22.000Z","trend":4,"direction":"Flat","device":"share2","type":"sgv"},{"_id":"57f7b68718a6c1577fc9e89c","sgv":111,"date":1475851822000,"dateString":"2016-10-07T14:50:22.000Z","trend":4,"direction":"Flat","device":"share2","type":"sgv"},{"_id":"57f7b55b18a6c1577fc9e89b","sgv":113,"date":1475851521000,"dateString":"2016-10-07T14:45:21.000Z","trend":4,"direction":"Flat","device":"share2","type":"sgv"},{"_id":"57f7b42f18a6c1577fc9e89a","sgv":120,"date":1475851221000,"dateString":"2016-10-07T14:40:21.000Z","trend":4,"direction":"Flat","device":"share2","type":"sgv"},{"_id":"57f7b30318a6c1577fc9e899","sgv":122,"date":1475850922000,"dateString":"2016-10-07T14:35:22.000Z","trend":4,"direction":"Flat","device":"share2","type":"sgv"},{"_id":"57f7b1d718a6c1577fc9e898","sgv":125,"date":1475850621000,"dateString":"2016-10-07T14:30:21.000Z","trend":4,"direction":"Flat","device":"share2","type":"sgv"},{"_id":"57f7b0ab18a6c1577fc9e894","sgv":126,"date":1475850323000,"dateString":"2016-10-07T14:25:23.000Z","trend":4,"direction":"Flat","device":"share2","type":"sgv"},{"_id":"57f7af7f18a6c1577fc9e893","sgv":127,"date":1475850022000,"dateString":"2016-10-07T14:20:22.000Z","trend":4,"direction":"Flat","device":"share2","type":"sgv"},{"_id":"57f7ae5318a6c1577fc9e892","sgv":129,"date":1475849722000,"dateString":"2016-10-07T14:15:22.000Z","trend":4,"direction":"Flat","device":"share2","type":"sgv"},{"_id":"57f7ad2718a6c1577fc9e88e","sgv":129,"date":1475849421000,"dateString":"2016-10-07T14:10:21.000Z","trend":4,"direction":"Flat","device":"share2","type":"sgv"},{"_id":"57f7abfb18a6c1577fc9e887","sgv":127,"date":1475849124000,"dateString":"2016-10-07T14:05:24.000Z","trend":4,"direction":"Flat","device":"share2","type":"sgv"},{"_id":"57f7aacf18a6c1577fc9e886","sgv":131,"date":1475848823000,"dateString":"2016-10-07T14:00:23.000Z","trend":4,"direction":"Flat","device":"share2","type":"sgv"},{"_id":"57f7a9a318a6c1577fc9e885","sgv":134,"date":1475848523000,"dateString":"2016-10-07T13:55:23.000Z","trend":4,"direction":"Flat","device":"share2","type":"sgv"},{"_id":"57f7a87718a6c1577fc9e881","sgv":133,"date":1475848222000,"dateString":"2016-10-07T13:50:22.000Z","trend":4,"direction":"Flat","device":"share2","type":"sgv"},{"_id":"57f7a74b18a6c1577fc9e880","sgv":132,"date":1475847922000,"dateString":"2016-10-07T13:45:22.000Z","trend":4,"direction":"Flat","device":"share2","type":"sgv"},{"_id":"57f7a61f18a6c1577fc9e87f","sgv":126,"date":1475847624000,"dateString":"2016-10-07T13:40:24.000Z","trend":4,"direction":"Flat","device":"share2","type":"sgv"},{"_id":"57f7a4f318a6c1577fc9e87b","sgv":126,"date":1475847321000,"dateString":"2016-10-07T13:35:21.000Z","trend":4,"direction":"Flat","device":"share2","type":"sgv"},{"_id":"57f7a3c718a6c1577fc9e87a","sgv":127,"date":1475847022000,"dateString":"2016-10-07T13:30:22.000Z","trend":4,"direction":"Flat","device":"share2","type":"sgv"},{"_id":"57f7a29b18a6c1577fc9e879","sgv":128,"date":1475846722000,"dateString":"2016-10-07T13:25:22.000Z","trend":4,"direction":"Flat","device":"share2","type":"sgv"},{"_id":"57f7a16f18a6c1577fc9e875","sgv":130,"date":1475846421000,"dateString":"2016-10-07T13:20:21.000Z","trend":4,"direction":"Flat","device":"share2","type":"sgv"},{"_id":"57f7a04318a6c1577fc9e874","sgv":135,"date":1475846122000,"dateString":"2016-10-07T13:15:22.000Z","trend":4,"direction":"Flat","device":"share2","type":"sgv"},{"_id":"57f79f1718a6c1577fc9e873","sgv":141,"date":1475845821000,"dateString":"2016-10-07T13:10:21.000Z","trend":4,"direction":"Flat","device":"share2","type":"sgv"},{"_id":"57f79deb18a6c1577fc9e86f","sgv":144,"date":1475845521000,"dateString":"2016-10-07T13:05:21.000Z","trend":4,"direction":"Flat","device":"share2","type":"sgv"},{"_id":"57f79cbf18a6c1577fc9e86e","sgv":144,"date":1475845222000,"dateString":"2016-10-07T13:00:22.000Z","trend":4,"direction":"Flat","device":"share2","type":"sgv"},{"_id":"57f79b9318a6c1577fc9e86d","sgv":145,"date":1475844921000,"dateString":"2016-10-07T12:55:21.000Z","trend":4,"direction":"Flat","device":"share2","type":"sgv"},{"_id":"57f79a6718a6c1577fc9e869","sgv":147,"date":1475844622000,"dateString":"2016-10-07T12:50:22.000Z","trend":4,"direction":"Flat","device":"share2","type":"sgv"},{"_id":"57f7993b18a6c1577fc9e865","sgv":149,"date":1475844322000,"dateString":"2016-10-07T12:45:22.000Z","trend":4,"direction":"Flat","device":"share2","type":"sgv"},{"_id":"57f7980f18a6c1577fc9e861","sgv":150,"date":1475844021000,"dateString":"2016-10-07T12:40:21.000Z","trend":4,"direction":"Flat","device":"share2","type":"sgv"},{"_id":"57f796e318a6c1577fc9e85d","sgv":151,"date":1475843722000,"dateString":"2016-10-07T12:35:22.000Z","trend":4,"direction":"Flat","device":"share2","type":"sgv"},{"_id":"57f795b718a6c1577fc9e85c","sgv":152,"date":1475843421000,"dateString":"2016-10-07T12:30:21.000Z","trend":4,"direction":"Flat","device":"share2","type":"sgv"},{"_id":"57f7948b18a6c1577fc9e857","sgv":152,"date":1475843121000,"dateString":"2016-10-07T12:25:21.000Z","trend":4,"direction":"Flat","device":"share2","type":"sgv"},{"_id":"57f7935f18a6c1577fc9e851","sgv":151,"date":1475842821000,"dateString":"2016-10-07T12:20:21.000Z","trend":4,"direction":"Flat","device":"share2","type":"sgv"},{"_id":"57f7923318a6c1577fc9e850","sgv":151,"date":1475842522000,"dateString":"2016-10-07T12:15:22.000Z","trend":4,"direction":"Flat","device":"share2","type":"sgv"},{"_id":"57f7910718a6c1577fc9e84f","sgv":152,"date":1475842221000,"dateString":"2016-10-07T12:10:21.000Z","trend":4,"direction":"Flat","device":"share2","type":"sgv"},{"_id":"57f78fdb18a6c1577fc9e84b","sgv":152,"date":1475841922000,"dateString":"2016-10-07T12:05:22.000Z","trend":4,"direction":"Flat","device":"share2","type":"sgv"},{"_id":"57f78eaf18a6c1577fc9e84a","sgv":152,"date":1475841622000,"dateString":"2016-10-07T12:00:22.000Z","trend":4,"direction":"Flat","device":"share2","type":"sgv"},{"_id":"57f78c5718a6c1577fc9e846","sgv":153,"date":1475841022000,"dateString":"2016-10-07T11:50:22.000Z","trend":4,"direction":"Flat","device":"share2","type":"sgv"},{"_id":"57f78b2b18a6c1577fc9e842","sgv":153,"date":1475840721000,"dateString":"2016-10-07T11:45:21.000Z","trend":4,"direction":"Flat","device":"share2","type":"sgv"},{"_id":"57f789ff18a6c1577fc9e841","sgv":154,"date":1475840422000,"dateString":"2016-10-07T11:40:22.000Z","trend":4,"direction":"Flat","device":"share2","type":"sgv"},{"_id":"57f788d318a6c1577fc9e83d","sgv":156,"date":1475840122000,"dateString":"2016-10-07T11:35:22.000Z","trend":4,"direction":"Flat","device":"share2","type":"sgv"},{"_id":"57f787a718a6c1577fc9e83c","sgv":155,"date":1475839821000,"dateString":"2016-10-07T11:30:21.000Z","trend":4,"direction":"Flat","device":"share2","type":"sgv"},{"_id":"57f7867b18a6c1577fc9e838","sgv":151,"date":1475839522000,"dateString":"2016-10-07T11:25:22.000Z","trend":4,"direction":"Flat","device":"share2","type":"sgv"},{"_id":"57f7854f18a6c1577fc9e837","sgv":148,"date":1475839223000,"dateString":"2016-10-07T11:20:23.000Z","trend":4,"direction":"Flat","device":"share2","type":"sgv"},{"_id":"57f7842318a6c1577fc9e836","sgv":146,"date":1475838922000,"dateString":"2016-10-07T11:15:22.000Z","trend":4,"direction":"Flat","device":"share2","type":"sgv"},{"_id":"57f782f718a6c1577fc9e835","sgv":144,"date":1475838622000,"dateString":"2016-10-07T11:10:22.000Z","trend":4,"direction":"Flat","device":"share2","type":"sgv"},{"_id":"57f781cb18a6c1577fc9e82e","sgv":145,"date":1475838322000,"dateString":"2016-10-07T11:05:22.000Z","trend":4,"direction":"Flat","device":"share2","type":"sgv"},{"_id":"57f7809f18a6c1577fc9e82a","sgv":147,"date":1475838021000,"dateString":"2016-10-07T11:00:21.000Z","trend":4,"direction":"Flat","device":"share2","type":"sgv"},{"_id":"57f77f7318a6c1577fc9e829","sgv":147,"date":1475837725000,"dateString":"2016-10-07T10:55:25.000Z","trend":4,"direction":"Flat","device":"share2","type":"sgv"},{"_id":"57f77e4718a6c1577fc9e828","sgv":148,"date":1475837422000,"dateString":"2016-10-07T10:50:22.000Z","trend":4,"direction":"Flat","device":"share2","type":"sgv"},{"_id":"57f77d1b18a6c1577fc9e824","sgv":149,"date":1475837123000,"dateString":"2016-10-07T10:45:23.000Z","trend":4,"direction":"Flat","device":"share2","type":"sgv"},{"_id":"57f77bef18a6c1577fc9e823","sgv":147,"date":1475836823000,"dateString":"2016-10-07T10:40:23.000Z","trend":4,"direction":"Flat","device":"share2","type":"sgv"},{"_id":"57f77ac318a6c1577fc9e81f","sgv":147,"date":1475836522000,"dateString":"2016-10-07T10:35:22.000Z","trend":4,"direction":"Flat","device":"share2","type":"sgv"},{"_id":"57f7799718a6c1577fc9e81d","sgv":146,"date":1475836223000,"dateString":"2016-10-07T10:30:23.000Z","trend":4,"direction":"Flat","device":"share2","type":"sgv"},{"_id":"57f7786b18a6c1577fc9e81a","sgv":148,"date":1475835922000,"dateString":"2016-10-07T10:25:22.000Z","trend":4,"direction":"Flat","device":"share2","type":"sgv"},{"_id":"57f7773f18a6c1577fc9e816","sgv":149,"date":1475835622000,"dateString":"2016-10-07T10:20:22.000Z","trend":4,"direction":"Flat","device":"share2","type":"sgv"},{"_id":"57f7761318a6c1577fc9e812","sgv":148,"date":1475835323000,"dateString":"2016-10-07T10:15:23.000Z","trend":4,"direction":"Flat","device":"share2","type":"sgv"},{"_id":"57f774e718a6c1577fc9e80f","sgv":146,"date":1475835021000,"dateString":"2016-10-07T10:10:21.000Z","trend":3,"direction":"FortyFiveUp","device":"share2","type":"sgv"},{"_id":"57f773bb18a6c1577fc9e80d","sgv":142,"date":1475834724000,"dateString":"2016-10-07T10:05:24.000Z","trend":3,"direction":"FortyFiveUp","device":"share2","type":"sgv"},{"_id":"57f7728f18a6c1577fc9e809","sgv":134,"date":1475834423000,"dateString":"2016-10-07T10:00:23.000Z","trend":3,"direction":"FortyFiveUp","device":"share2","type":"sgv"},{"_id":"57f7716218a6c1577fc9e808","sgv":128,"date":1475834121000,"dateString":"2016-10-07T09:55:21.000Z","trend":3,"direction":"FortyFiveUp","device":"share2","type":"sgv"},{"_id":"57f7703718a6c1577fc9e805","sgv":122,"date":1475833822000,"dateString":"2016-10-07T09:50:22.000Z","trend":3,"direction":"FortyFiveUp","device":"share2","type":"sgv"},{"_id":"57f76f0b18a6c1577fc9e803","sgv":111,"date":1475833522000,"dateString":"2016-10-07T09:45:22.000Z","trend":4,"direction":"Flat","device":"share2","type":"sgv"},{"_id":"57f76ddf18a6c1577fc9e7f2","sgv":107,"date":1475833222000,"dateString":"2016-10-07T09:40:22.000Z","trend":4,"direction":"Flat","device":"share2","type":"sgv"},{"_id":"57f76cb318a6c1577fc9e7f1","sgv":97,"date":1475832921000,"dateString":"2016-10-07T09:35:21.000Z","trend":4,"direction":"Flat","device":"share2","type":"sgv"},{"_id":"57f76a5a18a6c1577fc9e7f0","sgv":100,"date":1475832322000,"dateString":"2016-10-07T09:25:22.000Z","trend":4,"direction":"Flat","device":"share2","type":"sgv"},{"_id":"57f7692e18a6c1577fc9e7ef","sgv":103,"date":1475832021000,"dateString":"2016-10-07T09:20:21.000Z","trend":4,"direction":"Flat","device":"share2","type":"sgv"},{"_id":"57f7680218a6c1577fc9e7ee","sgv":105,"date":1475831722000,"dateString":"2016-10-07T09:15:22.000Z","trend":4,"direction":"Flat","device":"share2","type":"sgv"},{"_id":"57f766d618a6c1577fc9e7ed","sgv":102,"date":1475831422000,"dateString":"2016-10-07T09:10:22.000Z","trend":4,"direction":"Flat","device":"share2","type":"sgv"},{"_id":"57f765aa18a6c1577fc9e7ec","sgv":104,"date":1475831122000,"dateString":"2016-10-07T09:05:22.000Z","trend":4,"direction":"Flat","device":"share2","type":"sgv"},{"_id":"57f7647e18a6c1577fc9e7eb","sgv":106,"date":1475830821000,"dateString":"2016-10-07T09:00:21.000Z","trend":4,"direction":"Flat","device":"share2","type":"sgv"},{"_id":"57f7635218a6c1577fc9e7ea","sgv":107,"date":1475830521000,"dateString":"2016-10-07T08:55:21.000Z","trend":4,"direction":"Flat","device":"share2","type":"sgv"},{"_id":"57f7622718a6c1577fc9e7e9","sgv":107,"date":1475830222000,"dateString":"2016-10-07T08:50:22.000Z","trend":4,"direction":"Flat","device":"share2","type":"sgv"},{"_id":"57f760fa18a6c1577fc9e7e8","sgv":109,"date":1475829922000,"dateString":"2016-10-07T08:45:22.000Z","trend":4,"direction":"Flat","device":"share2","type":"sgv"},{"_id":"57f75fce18a6c1577fc9e7e7","sgv":110,"date":1475829622000,"dateString":"2016-10-07T08:40:22.000Z","trend":4,"direction":"Flat","device":"share2","type":"sgv"},{"_id":"57f75ea218a6c1577fc9e7e6","sgv":109,"date":1475829322000,"dateString":"2016-10-07T08:35:22.000Z","trend":4,"direction":"Flat","device":"share2","type":"sgv"},{"_id":"57f75d7618a6c1577fc9e7e5","sgv":106,"date":1475829023000,"dateString":"2016-10-07T08:30:23.000Z","trend":4,"direction":"Flat","device":"share2","type":"sgv"},{"_id":"57f75c4a18a6c1577fc9e7e4","sgv":105,"date":1475828721000,"dateString":"2016-10-07T08:25:21.000Z","trend":5,"direction":"FortyFiveDown","device":"share2","type":"sgv"},{"_id":"57f75b1f18a6c1577fc9e7e3","sgv":109,"date":1475828422000,"dateString":"2016-10-07T08:20:22.000Z","trend":4,"direction":"Flat","device":"share2","type":"sgv"},{"_id":"57f759f218a6c1577fc9e7e2","sgv":115,"date":1475828122000,"dateString":"2016-10-07T08:15:22.000Z","trend":4,"direction":"Flat","device":"share2","type":"sgv"},{"_id":"57f758c618a6c1577fc9e7e1","sgv":123,"date":1475827821000,"dateString":"2016-10-07T08:10:21.000Z","trend":4,"direction":"Flat","device":"share2","type":"sgv"},{"_id":"57f7579a18a6c1577fc9e7e0","sgv":124,"date":1475827522000,"dateString":"2016-10-07T08:05:22.000Z","trend":4,"direction":"Flat","device":"share2","type":"sgv"},{"_id":"57f7566e18a6c1577fc9e7df","sgv":117,"date":1475827223000,"dateString":"2016-10-07T08:00:23.000Z","trend":4,"direction":"Flat","device":"share2","type":"sgv"},{"_id":"57f7554318a6c1577fc9e7de","sgv":113,"date":1475826922000,"dateString":"2016-10-07T07:55:22.000Z","trend":5,"direction":"FortyFiveDown","device":"share2","type":"sgv"},{"_id":"57f7541618a6c1577fc9e7dd","sgv":121,"date":1475826622000,"dateString":"2016-10-07T07:50:22.000Z","trend":5,"direction":"FortyFiveDown","device":"share2","type":"sgv"},{"_id":"57f752ea18a6c1577fc9e7dc","sgv":126,"date":1475826322000,"dateString":"2016-10-07T07:45:22.000Z","trend":4,"direction":"Flat","device":"share2","type":"sgv"},{"_id":"57f751bf18a6c1577fc9e7db","sgv":140,"date":1475826023000,"dateString":"2016-10-07T07:40:23.000Z","trend":4,"direction":"Flat","device":"share2","type":"sgv"},{"_id":"57f7509218a6c1577fc9e7da","sgv":141,"date":1475825722000,"dateString":"2016-10-07T07:35:22.000Z","trend":4,"direction":"Flat","device":"share2","type":"sgv"},{"_id":"57f74f6618a6c1577fc9e7d9","sgv":139,"date":1475825423000,"dateString":"2016-10-07T07:30:23.000Z","trend":4,"direction":"Flat","device":"share2","type":"sgv"},{"_id":"57f74e3a18a6c1577fc9e7d8","sgv":139,"date":1475825123000,"dateString":"2016-10-07T07:25:23.000Z","trend":4,"direction":"Flat","device":"share2","type":"sgv"},{"_id":"57f74d0e18a6c1577fc9e7d7","sgv":141,"date":1475824822000,"dateString":"2016-10-07T07:20:22.000Z","trend":4,"direction":"Flat","device":"share2","type":"sgv"},{"_id":"57f74be218a6c1577fc9e7d6","sgv":147,"date":1475824522000,"dateString":"2016-10-07T07:15:22.000Z","trend":4,"direction":"Flat","device":"share2","type":"sgv"},{"_id":"57f74ab618a6c1577fc9e7d5","sgv":152,"date":1475824222000,"dateString":"2016-10-07T07:10:22.000Z","trend":4,"direction":"Flat","device":"share2","type":"sgv"},{"_id":"57f7498b18a6c1577fc9e7d4","sgv":152,"date":1475823922000,"dateString":"2016-10-07T07:05:22.000Z","trend":4,"direction":"Flat","device":"share2","type":"sgv"},{"_id":"57f7485e18a6c1577fc9e7d3","sgv":152,"date":1475823621000,"dateString":"2016-10-07T07:00:21.000Z","trend":4,"direction":"Flat","device":"share2","type":"sgv"},{"_id":"57f7473218a6c1577fc9e7d2","sgv":154,"date":1475823322000,"dateString":"2016-10-07T06:55:22.000Z","trend":4,"direction":"Flat","device":"share2","type":"sgv"},{"_id":"57f7460618a6c1577fc9e7d1","sgv":154,"date":1475823021000,"dateString":"2016-10-07T06:50:21.000Z","trend":4,"direction":"Flat","device":"share2","type":"sgv"},{"_id":"57f744da18a6c1577fc9e7d0","sgv":155,"date":1475822722000,"dateString":"2016-10-07T06:45:22.000Z","trend":4,"direction":"Flat","device":"share2","type":"sgv"},{"_id":"57f743ae18a6c1577fc9e7cf","sgv":152,"date":1475822422000,"dateString":"2016-10-07T06:40:22.000Z","trend":4,"direction":"Flat","device":"share2","type":"sgv"},{"_id":"57f7428218a6c1577fc9e7ce","sgv":155,"date":1475822122000,"dateString":"2016-10-07T06:35:22.000Z","trend":4,"direction":"Flat","device":"share2","type":"sgv"},{"_id":"57f7415618a6c1577fc9e7cd","sgv":152,"date":1475821822000,"dateString":"2016-10-07T06:30:22.000Z","trend":3,"direction":"FortyFiveUp","device":"share2","type":"sgv"},{"_id":"57f7402a18a6c1577fc9e7cc","sgv":154,"date":1475821523000,"dateString":"2016-10-07T06:25:23.000Z","trend":3,"direction":"FortyFiveUp","device":"share2","type":"sgv"},{"_id":"57f73efe18a6c1577fc9e7cb","sgv":148,"date":1475821221000,"dateString":"2016-10-07T06:20:21.000Z","trend":3,"direction":"FortyFiveUp","device":"share2","type":"sgv"},{"_id":"57f73dd218a6c1577fc9e7ca","sgv":137,"date":1475820924000,"dateString":"2016-10-07T06:15:24.000Z","trend":3,"direction":"FortyFiveUp","device":"share2","type":"sgv"},{"_id":"57f73ca618a6c1577fc9e7c9","sgv":122,"date":1475820622000,"dateString":"2016-10-07T06:10:22.000Z","trend":4,"direction":"Flat","device":"share2","type":"sgv"},{"_id":"57f73b7a18a6c1577fc9e7c8","sgv":118,"date":1475820322000,"dateString":"2016-10-07T06:05:22.000Z","trend":4,"directio
