[{"iob":-1.131,"activity":-0.0088,"bolussnooze":0,"basaliob":-1.131,"netbasalinsulin":-1.6,"hightempinsulin":0,"time":"2016-10-15T15:59:07.000Z"},{"iob":-1.263,"activity":-0.0094,"bolussnooze":0,"basaliob":-1.263,"netbasalinsulin":-1.8,"hightempinsulin":0,"time":"2016-10-15T16:04:07.000Z"},{"iob":-1.337,"activity":-0.0102,"bolussnooze":0,"basaliob":-1.337,"netbasalinsulin":-1.95,"hightempinsulin":0,"time":"2016-10-15T16:09:07.000Z"},{"iob":-1.302,"activity":-0.0109,"bolussnooze":0,"basaliob":-1.302,"netbasalinsulin":-2,"hightempinsulin":0,"time":"2016-10-15T16:14:07.000Z"},{"iob":-1.211,"activity":-0.0111,"bolussnooze":0,"basaliob":-1.211,"netbasalinsulin":-2,"hightempinsulin":0,"time":"2016-10-15T16:19:07.000Z"},{"iob":-1.114,"activity":-0.011,"bolussnooze":0,"basaliob":-1.114,"netbasalinsulin":-2,"hightempinsulin":0,"time":"2016-10-15T16:24:07.000Z"},{"iob":-1.012,"activity":-0.0139,"bolussnooze":0,"basaliob":-1.012,"netbasalinsulin":-1.85,"hightempinsulin":0,"time":"2016-10-15T16:29:07.000Z"},{"iob":-0.907,"activity":-0.013,"bolussnooze":0,"basaliob":-0.907,"netbasalinsulin":-1.85,"hightempinsulin":0,"time":"2016-10-15T16:34:07.000Z"},{"iob":-0.802,"activity":-0.0114,"bolussnooze":0,"basaliob":-0.802,"netbasalinsulin":-1.85,"hightempinsulin":0,"time":"2016-10-15T16:39:07.000Z"},{"iob":-0.698,"activity":-0.0103,"bolussnooze":0,"basaliob":-0.698,"netbasalinsulin":-1.8,"hightempinsulin":0,"time":"2016-10-15T16:44:07.000Z"},{"iob":-0.598,"activity":-0.0085,"bolussnooze":0,"basaliob":-0.598,"netbasalinsulin":-1.75,"hightempinsulin":0,"time":"2016-10-15T16:49:07.000Z"},{"iob":-0.503,"activity":-0.0073,"bolussnooze":0,"basaliob":-0.503,"netbasalinsulin":-1.65,"hightempinsulin":0,"time":"2016-10-15T16:54:07.000Z"},{"iob":-0.416,"activity":-0.0044,"bolussnooze":0,"basaliob":-0.416,"netbasalinsulin":-1.6,"hightempinsulin":0,"time":"2016-10-15T16:59:07.000Z"},{"iob":-0.338,"activity":-0.0011,"bolussnooze":0,"basaliob":-0.338,"netbasalinsulin":-1.55,"hightempinsulin":0,"time":"2016-10-15T17:04:07.000Z"},{"iob":-0.269,"activity":0.002,"bolussnooze":0,"basaliob":-0.269,"netbasalinsulin":-1.5,"hightempinsulin":0,"time":"2016-10-15T17:09:07.000Z"},{"iob":-0.21,"activity":0.0062,"bolussnooze":0,"basaliob":-0.21,"netbasalinsulin":-1.5,"hightempinsulin":0,"time":"2016-10-15T17:14:07.000Z"},{"iob":-0.159,"activity":0.0092,"bolussnooze":0,"basaliob":-0.159,"netbasalinsulin":-1.45,"hightempinsulin":0,"time":"2016-10-15T17:19:07.000Z"},{"iob":-0.116,"activity":0.0108,"bolussnooze":0,"basaliob":-0.116,"netbasalinsulin":-1.35,"hightempinsulin":0,"time":"2016-10-15T17:24:07.000Z"},{"iob":-0.082,"activity":0.0123,"bolussnooze":0,"basaliob":-0.082,"netbasalinsulin":-1.25,"hightempinsulin":0,"time":"2016-10-15T17:29:07.000Z"},{"iob":-0.055,"activity":0.0134,"bolussnooze":0,"basaliob":-0.055,"netbasalinsulin":-1.15,"hightempinsulin":0,"time":"2016-10-15T17:34:07.000Z"},{"iob":-0.034,"activity":0.0143,"bolussnooze":0,"basaliob":-0.034,"netbasalinsulin":-1.05,"hightempinsulin":0,"time":"2016-10-15T17:39:07.000Z"},{"iob":-0.02,"activity":0.0136,"bolussnooze":0,"basaliob":-0.02,"netbasalinsulin":-0.9,"hightempinsulin":0,"time":"2016-10-15T17:44:07.000Z"},{"iob":-0.01,"activity":0.0113,"bolussnooze":0,"basaliob":-0.01,"netbasalinsulin":-0.7,"hightempinsulin":0,"time":"2016-10-15T17:49:07.000Z"},{"iob":-0.004,"activity":0.0098,"bolussnooze":0,"basaliob":-0.004,"netbasalinsulin":-0.55,"hightempinsulin":0,"time":"2016-10-15T17:54:07.000Z"},{"iob":-0.001,"activity":0.0077,"bolussnooze":0,"basaliob":-0.001,"netbasalinsulin":-0.4,"hightempinsulin":0,"time":"2016-10-15T17:59:07.000Z"},{"iob":0,"activity":0.0041,"bolussnooze":0,"basaliob":0,"netbasalinsulin":-0.2,"hightempinsulin":0,"time":"2016-10-15T18:04:07.000Z"},{"iob":0,"activity":0.0011,"bolussnooze":0,"basaliob":0,"netbasalinsulin":-0.05,"hightempinsulin":0,"time":"2016-10-15T18:09:07.000Z"},{"iob":0,"activity":0,"bolussnooze":0,"basaliob":0,"netbasalinsulin":0,"hightempinsulin":0,"time":"2016-10-15T18:14:07.000Z"},{"iob":0,"activity":0,"bolussnooze":0,"basaliob":0,"netbasalinsulin":0,"hightempinsulin":0,"time":"2016-10-15T18:19:07.000Z"},{"iob":0,"activity":0,"bolussnooze":0,"basaliob":0,"netbasalinsulin":0,"hightempinsulin":0,"time":"2016-10-15T18:24:07.000Z"}]
